README.md
setup.py
git_profile_manager/__init__.py
git_profile_manager/__version__.py
git_profile_manager/common_args.py
git_profile_manager/configparser.py
git_profile_manager/utils.py
git_profile_manager.egg-info/PKG-INFO
git_profile_manager.egg-info/SOURCES.txt
git_profile_manager.egg-info/dependency_links.txt
git_profile_manager.egg-info/entry_points.txt
git_profile_manager.egg-info/top_level.txt
git_profile_manager/commands/__init__.py
git_profile_manager/commands/apply_profile.py
git_profile_manager/commands/create_profile.py
git_profile_manager/commands/current_profile.py
git_profile_manager/commands/global_config.py
git_profile_manager/commands/list_profiles.py
git_profile_manager/commands/remove_profile.py
git_profile_manager/commands/use_profile.py