Metadata-Version: 2.1
Name: git-profile-manager
Version: 0.0.4.post1
Summary: A git extension to allow you manage multiple git profiles on your workstation
Home-page: https://github.com/MeNsaaH/git-profile-manager
Author: Mmadu Manasseh
Author-email: mmadumanasseh@gmail.com
License: MIT
Project-URL: Source, https://github.com/MeNsaaH/git-profile-manager
Platform: UNKNOWN
Classifier: Programming Language :: Python :: 3
Classifier: License :: OSI Approved :: MIT License
Classifier: Operating System :: OS Independent
Requires-Python: >=3.0
